grayscale_py/__init__.py
grayscale_py/grayscale.cp312-win_amd64.pyd
grayscale_py/grayscale.cpp
grayscale_py/stb_image.h
grayscale_py/stb_image_write.h
grayscale_py-0.1.0.dist-info/licenses/LICENSE
grayscale_py-0.1.0.dist-info/METADATA
grayscale_py-0.1.0.dist-info/WHEEL
grayscale_py-0.1.0.dist-info/top_level.txt
grayscale_py-0.1.0.dist-info/RECORD
